spaceone/__init__.py
spaceone/statistics/__init__.py
spaceone/statistics/api/__init__.py
spaceone/statistics/api/v1/__init__.py
spaceone/statistics/api/v1/history.py
spaceone/statistics/api/v1/resource.py
spaceone/statistics/api/v1/schedule.py
spaceone/statistics/conf/__init__.py
spaceone/statistics/conf/global_conf.py
spaceone/statistics/conf/proto_conf.py
spaceone/statistics/connector/__init__.py
spaceone/statistics/connector/identity_connector.py
spaceone/statistics/connector/service_connector.py
spaceone/statistics/error/__init__.py
spaceone/statistics/error/history.py
spaceone/statistics/error/resource.py
spaceone/statistics/error/schedule.py
spaceone/statistics/info/__init__.py
spaceone/statistics/info/common_info.py
spaceone/statistics/info/history_info.py
spaceone/statistics/info/resource_info.py
spaceone/statistics/info/schedule_info.py
spaceone/statistics/lib/__init__.py
spaceone/statistics/manager/__init__.py
spaceone/statistics/manager/history_manager.py
spaceone/statistics/manager/resource_manager.py
spaceone/statistics/manager/schedule_manager.py
spaceone/statistics/model/__init__.py
spaceone/statistics/model/history_model.py
spaceone/statistics/model/schedule_model.py
spaceone/statistics/scheduler/__init__.py
spaceone/statistics/scheduler/stat_hourly_scheduler.py
spaceone/statistics/service/__init__.py
spaceone/statistics/service/history_service.py
spaceone/statistics/service/resource_service.py
spaceone/statistics/service/schedule_service.py
spaceone/statistics/task/__init__.py
spaceone/statistics/task/stat_hourly_scheduler.py
spaceone_statistics-1.12.0.dist-info/METADATA
spaceone_statistics-1.12.0.dist-info/WHEEL
spaceone_statistics-1.12.0.dist-info/top_level.txt
spaceone_statistics-1.12.0.dist-info/RECORD
