Metadata-Version: 2.1
Name: spaceone-statistics
Version: 1.12.0
Summary: SpaceONE statistics service
Home-page: https://www.spaceone.dev/
Author: MEGAZONE SpaceONE Team
Author-email: admin@spaceone.dev
License: Apache License 2.0
Platform: UNKNOWN
Requires-Dist: spaceone-core
Requires-Dist: spaceone-api
Requires-Dist: mongoengine
Requires-Dist: pandas
Requires-Dist: numpy
Requires-Dist: python-consul
Requires-Dist: redis
